setup.py
myPkg/__init__.py
myPkg/myModule3.py
newLibrary.egg-info/PKG-INFO
newLibrary.egg-info/SOURCES.txt
newLibrary.egg-info/dependency_links.txt
newLibrary.egg-info/top_level.txt