Metadata-Version: 1.0
Name: newLibrary
Version: 1.2.5
Summary: My first Python library
Home-page: UNKNOWN
Author: Hamed
Author-email: UNKNOWN
License: UNKNOWN
Platform: UNKNOWN
